ph/__init__.py
ph/_version.py
ph/tabulate.py
ph-0.4.1.dist-info/LICENSE
ph-0.4.1.dist-info/METADATA
ph-0.4.1.dist-info/WHEEL
ph-0.4.1.dist-info/entry_points.txt
ph-0.4.1.dist-info/top_level.txt
ph-0.4.1.dist-info/RECORD
