Metadata-Version: 2.1
Name: ph
Version: 0.4.1
Summary: ph - the tabular data shell tool
Home-page: https://github.com/pgdr/ph
Author: PG Drange
Author-email: pgdr@equinor.com
Maintainer: PG Drange <pgdr@equinor.com>
License: MIT
Project-URL: Bug Tracker, https://github.com/pgdr/ph/issues
Project-URL: Documentation, https://github.com/pgdr/ph/blob/master/README.md
Project-URL: Source Code, https://github.com/pgdr/ph
Keywords: tabular data,pandas,csv,pipeline,unix,command line tool
Platform: UNKNOWN
Requires-Dist: pandas
Provides-Extra: complete
Requires-Dist: cufflinks ; extra == 'complete'
Requires-Dist: gpxpy ; extra == 'complete'
Requires-Dist: matplotlib ; extra == 'complete'
Requires-Dist: numpy ; extra == 'complete'
Requires-Dist: pandas ; extra == 'complete'
Requires-Dist: pyarrow ; extra == 'complete'
Requires-Dist: scikit-learn ; extra == 'complete'
Requires-Dist: xlrd ; extra == 'complete'
Requires-Dist: xlwt ; extra == 'complete'
Provides-Extra: data
Requires-Dist: pandas ; extra == 'data'
Requires-Dist: scikit-learn ; extra == 'data'
Provides-Extra: gpx
Requires-Dist: pandas ; extra == 'gpx'
Requires-Dist: gpxpy ; extra == 'gpx'
Provides-Extra: iplot
Requires-Dist: pandas ; extra == 'iplot'
Requires-Dist: cufflinks ; extra == 'iplot'
Provides-Extra: math
Requires-Dist: pandas ; extra == 'math'
Requires-Dist: numpy ; extra == 'math'
Provides-Extra: minimum
Requires-Dist: pandas ; extra == 'minimum'
Provides-Extra: parquet
Requires-Dist: pandas ; extra == 'parquet'
Requires-Dist: pyarrow ; extra == 'parquet'
Provides-Extra: plot
Requires-Dist: pandas ; extra == 'plot'
Requires-Dist: matplotlib ; extra == 'plot'
Provides-Extra: xls
Requires-Dist: pandas ; extra == 'xls'
Requires-Dist: xlrd ; extra == 'xls'
Provides-Extra: xlsw
Requires-Dist: pandas ; extra == 'xlsw'
Requires-Dist: xlrd ; extra == 'xlsw'
Requires-Dist: xlwt ; extra == 'xlsw'
